llm_compression/__init__.py
llm_compression/arithmetic_coding.py
llm_compression/llama_model.py
llm_compression/probability_model.py
llm_compression-0.1.2.dist-info/LICENSE
llm_compression-0.1.2.dist-info/METADATA
llm_compression-0.1.2.dist-info/WHEEL
llm_compression-0.1.2.dist-info/RECORD
