Metadata-Version: 2.1
Name: llm-compression
Version: 0.1.2
Summary: Arithmetic compression using Llama LLM models
License: GPL3
Author: OdoctorG
Author-email: grenoscar@gmail.com
Requires-Python: >=3.10
Classifier: License :: Other/Proprietary License
Classifier: Programming Language :: Python :: 3
Classifier: Programming Language :: Python :: 3.10
Classifier: Programming Language :: Python :: 3.11
Classifier: Programming Language :: Python :: 3.12
Classifier: Programming Language :: Python :: 3.13
Requires-Dist: llama-cpp-python (>=0.3.8,<0.4.0)
Requires-Dist: numpy (>=2.2.5,<3.0.0)
